{
  "variant": "obcache",
  "description": "OBCache 默认配置",
  "runnable": true,
  "repo_path": ".",
  "model_family": "OBVGGT",
  "model_name": "StreamVGGT",
  "env_name": "obvggt",
  "adapter": "run_obvggt.py",
  "supported_tasks": [
    "monodepth",
    "video_depth",
    "mv_recon",
    "pose_co3d"
  ],
  "kv_policy_summary": "Joint V+K scoring with sink/recent/heavy token budgets.",
  "kv_cache_enable": true,
  "kv_cache_cfg": {
    "enable": true,
    "method": "obcvk",
    "p": 2,
    "use_vnorm": true,
    "num_sink_frames": 1,
    "num_recent_frames": 2,
    "num_heavy_frames": 4,
    "probe_mode": true,
    "num_patch_probes": 8
  },
  "model": "StreamVGGT",
  "checkpoint": "ckpt/checkpoints.pth"
}
